ngohub/__init__.py
ngohub/core.py
ngohub/exceptions.py
ngohub/network.py
ngohub/models/__init__.py
ngohub/models/checks.py
ngohub/models/core.py
ngohub/models/entities.py
ngohub/models/locations.py
ngohub/models/nomenclatures.py
ngohub/models/organization.py
ngohub/models/public.py
ngohub/models/user.py
ngohub/normalization/__init__.py
ngohub/normalization/organization.py
ngohub/normalization/processors.py
ngohub/normalization/public.py
ngohub/normalization/user.py
NGOHub-0.0.10.dist-info/LICENSE
NGOHub-0.0.10.dist-info/METADATA
NGOHub-0.0.10.dist-info/WHEEL
NGOHub-0.0.10.dist-info/top_level.txt
NGOHub-0.0.10.dist-info/RECORD
