Metadata-Version: 2.2
Name: NGOHub
Version: 0.0.10
Summary: Python client for ngohub.ro API
Project-URL: Homepage, https://github.com/code4romania/pyngohub/
Project-URL: Issues, https://github.com/code4romania/pyngohub/issues
Project-URL: Changelog, https://github.com/code4romania/pyngohub/blob/main/CHANGELOG.md
Project-URL: Download, https://github.com/code4romania/pyngohub/tags
Classifier: Development Status :: 1 - Planning
Classifier: Intended Audience :: Developers
Classifier: License :: OSI Approved :: Mozilla Public License 2.0 (MPL 2.0)
Classifier: Operating System :: OS Independent
Classifier: Programming Language :: Python :: 3
Classifier: Topic :: Software Development
Classifier: Topic :: Software Development :: Libraries
Classifier: Topic :: Software Development :: Libraries :: Python Modules
Requires-Python: >=3.12
License-File: LICENSE
